CHANGES
LICENSE
MANIFEST.in
Makefile
README
completion.bash
main.py
setup.cfg
setup.py
continuity/__init__.py
continuity.egg-info/PKG-INFO
continuity.egg-info/SOURCES.txt
continuity.egg-info/dependency_links.txt
continuity.egg-info/entry_points.txt
continuity.egg-info/requires.txt
continuity.egg-info/top_level.txt
continuity/cli/__init__.py
continuity/cli/commons.py
continuity/cli/github.py
continuity/cli/jira.py
continuity/cli/pt.py
continuity/cli/utils.py
continuity/services/__init__.py
continuity/services/commons.py
continuity/services/git.py
continuity/services/github.py
continuity/services/jira.py
continuity/services/pt.py
continuity/services/utils.py
docs/conf.py
docs/git-backlog.rst
docs/git-continuity.rst
docs/git-finish.rst
docs/git-issue.rst
docs/git-issues.rst
docs/git-review.rst
docs/git-start.rst
docs/git-story.rst
docs/git-tasks.rst
docs/index.rst