Metadata-Version: 1.0
Name: continuity
Version: 0.10.0
Summary: Continuous dev flow via GitHub Issues, Pivotal Tracker, or JIRA.
Home-page: http://github.com/jzempel/continuity
Author: Jonathan Zempel
Author-email: jzempel@gmail.com
License: BSD
Platform: UNKNOWN
